TheLadder/__init__.py
TheLadder/TheLadder.py
TheLadder-0.1.0.dist-info/DESCRIPTION.rst
TheLadder-0.1.0.dist-info/METADATA
TheLadder-0.1.0.dist-info/metadata.json
TheLadder-0.1.0.dist-info/RECORD
TheLadder-0.1.0.dist-info/top_level.txt
TheLadder-0.1.0.dist-info/WHEEL
