Metadata-Version: 2.0
Name: TheLadder
Version: 0.1.0
Summary: A competitive ladder app in Python.
Home-page: https://github.com/six0h/TheLadder
Author: Cody Halovich
Author-email: cody@sixohquad.com
License: MIT
Keywords: TheLadder
Platform: UNKNOWN
Classifier: Development Status :: 2 - Pre-Alpha
Classifier: Intended Audience :: Developers
Classifier: License :: OSI Approved :: MIT License
Classifier: Natural Language :: English
Classifier: Programming Language :: Python :: 2
Classifier: Programming Language :: Python :: 2.6
Classifier: Programming Language :: Python :: 2.7
Classifier: Programming Language :: Python :: 3
Classifier: Programming Language :: Python :: 3.3
Classifier: Programming Language :: Python :: Implementation :: PyPy
